texhelper/__init__.py
texhelper/bibtex.py
texhelper-0.1.1.dist-info/LICENSE
texhelper-0.1.1.dist-info/METADATA
texhelper-0.1.1.dist-info/WHEEL
texhelper-0.1.1.dist-info/top_level.txt
texhelper-0.1.1.dist-info/RECORD
