Metadata-Version: 2.1
Name: texhelper
Version: 0.1.1
Summary: A Python library for processing Tex files, such as formatting BibTeX titles, capitalizing words, and more.
Author: Shuhong Dai
Author-email: daishuhong02@gmail.com
License: Apache License 2.0
Classifier: Programming Language :: Python :: 3
Classifier: License :: OSI Approved :: Apache Software License
Classifier: Operating System :: OS Independent
Classifier: Intended Audience :: Developers
Classifier: License :: OSI Approved :: Apache Software License
Classifier: Programming Language :: Python :: 3 :: Only
Requires-Python: >=3.10
License-File: LICENSE
Requires-Dist: numpy
Requires-Dist: pytest
Requires-Dist: regex
Requires-Dist: pandas
Requires-Dist: pyyaml
Requires-Dist: click
Requires-Dist: requests
Requires-Dist: tqdm
Requires-Dist: matplotlib
Requires-Dist: beautifulsoup4
